ormm/__init__.py
ormm/markov/__init__.py
ormm/markov/main.py
ormm/mathprog/__init__.py
ormm/mathprog/milp.py
ormm/mathprog/scheduling.py
ormm/network/__init__.py
ormm/network/main.py
ormm-0.1.0.dist-info/LICENSE
ormm-0.1.0.dist-info/METADATA
ormm-0.1.0.dist-info/WHEEL
ormm-0.1.0.dist-info/top_level.txt
ormm-0.1.0.dist-info/RECORD
