Metadata-Version: 2.1
Name: ormm
Version: 0.1.0
Summary: A collection of Operations Research Models & Methods
Home-page: https://github.com/egbuck/ormm
Author: Ethan Buck
Author-email: egbuck96@gmail.com
License: UNKNOWN
Project-URL: Documentation, https://ormm.readthedocs.io/en/stable/
Platform: UNKNOWN
Classifier: Programming Language :: Cython
Classifier: Programming Language :: Python
Classifier: Programming Language :: Python :: 3
Classifier: Programming Language :: Python :: 3.6
Classifier: Programming Language :: Python :: 3.7
Classifier: Programming Language :: Python :: 3.8
Classifier: License :: OSI Approved :: GNU General Public License v3 or later (GPLv3+)
Classifier: Operating System :: OS Independent
Classifier: Development Status :: 2 - Pre-Alpha
Classifier: Environment :: Console
Classifier: Intended Audience :: Science/Research
Classifier: Intended Audience :: Manufacturing
Classifier: Intended Audience :: End Users/Desktop
Classifier: Intended Audience :: Education
Classifier: Topic :: Education
Classifier: Topic :: Scientific/Engineering :: Mathematics
Requires-Dist: pyomo (>=5.0)
Requires-Dist: pandas (>=1)
Requires-Dist: quantecon (>=0.4)
Provides-Extra: dev
Requires-Dist: pytest (>=6.0) ; extra == 'dev'
Requires-Dist: sphinx (>=3.1.2) ; extra == 'dev'
Requires-Dist: sphinx-rtd-theme (>=0.5.0) ; extra == 'dev'
Requires-Dist: twine (>=3.2.0) ; extra == 'dev'
Requires-Dist: flake8 (>=3.8.3) ; extra == 'dev'
Requires-Dist: pytest-cov (>=2.10.0) ; extra == 'dev'
Requires-Dist: codecov (>=2.1.8) ; extra == 'dev'
